<?xml version="1.0" encoding="utf-8" ?>
<dwsync>
<file name="24kGoldn - Mood.png" server="C:/Xampp/htdocs/ProjectWeb1/" local="132998522197480146" remote="132998522190000000" Dst="0" />
<file name="Ava Max - Salt.png" server="C:/Xampp/htdocs/ProjectWeb1/" local="132998534608957892" remote="132998534600000000" Dst="0" />
<file name="Dua Lipa - Don't Start Now.png" server="C:/Xampp/htdocs/ProjectWeb1/" local="132998533444962389" remote="132998533440000000" Dst="0" />
<file name="Imagine Dragons - Bones.png" server="C:/Xampp/htdocs/ProjectWeb1/" local="132998543037137529" remote="132998543030000000" Dst="0" />
<file name="inverness & William Bolton - Lost My Mind.png" server="C:/Xampp/htdocs/ProjectWeb1/" local="132998540555200691" remote="132998540550000000" Dst="0" />
<file name="Jonasu - Black Magic.png" server="C:/Xampp/htdocs/ProjectWeb1/" local="132998541707312644" remote="132998541700000000" Dst="0" />
<file name="Machine Gun Kelly ft. blackbear - my ex's best friend.png" server="C:/Xampp/htdocs/ProjectWeb1/" local="132998530188394193" remote="132998530180000000" Dst="0" />
<file name="Martin Garrix & Pierce Fulton feat. Mike Shinoda - Waiting For Tomorrow.png" server="C:/Xampp/htdocs/ProjectWeb1/" local="132998544722763432" remote="132998544720000000" Dst="0" />
<file name="Måneskin - Beggin’ .png" server="C:/Xampp/htdocs/ProjectWeb1/" local="132998517508793984" remote="132998517500000000" Dst="0" />
<file name="Olivia Rodrigo - good 4 u.png" server="C:/Xampp/htdocs/ProjectWeb1/" local="132998537436213678" remote="132998537430000000" Dst="0" />
<file name="Shawn Mendes - Theres Nothing Holdin Me Back.png" server="C:/Xampp/htdocs/ProjectWeb1/" local="132998512641116388" remote="132998512640000000" Dst="0" />
<file name="The Chainsmokers - High.png" server="C:/Xampp/htdocs/ProjectWeb1/" local="132998519809998537" remote="132998519800000000" Dst="0" />
<file name="Tim Legend - soda city funk.png" server="C:/Xampp/htdocs/ProjectWeb1/" local="132998526193152148" remote="132998526190000000" Dst="0" />
<file name="VALORANT - Can’t Slow Me Down.png" server="C:/Xampp/htdocs/ProjectWeb1/" local="132998539821458740" remote="132998539820000000" Dst="0" />
<file name="Walk off the Earth Ft. D Smoke - Bet On Me.png" server="C:/Xampp/htdocs/ProjectWeb1/" local="132998523637922073" remote="132998523630000000" Dst="0" />
<file name="音樂.txt" server="C:/Xampp/htdocs/ProjectWeb1/" local="132998554795064142" remote="132998554790000000" Dst="0" />
</dwsync>